magicgui/__init__.py
magicgui/_type_resolution.py
magicgui/_util.py
magicgui/application.py
magicgui/experimental.py
magicgui/py.typed
magicgui/signature.py
magicgui/tqdm.py
magicgui/types.py
magicgui/backends/__init__.py
magicgui/backends/_ipynb/__init__.py
magicgui/backends/_ipynb/application.py
magicgui/backends/_ipynb/widgets.py
magicgui/backends/_qtpy/__init__.py
magicgui/backends/_qtpy/application.py
magicgui/backends/_qtpy/widgets.py
magicgui/schema/__init__.py
magicgui/schema/_guiclass.py
magicgui/schema/_ui_field.py
magicgui/type_map/__init__.py
magicgui/type_map/_magicgui.py
magicgui/type_map/_type_map.py
magicgui/widgets/__init__.py
magicgui/widgets/_concrete.py
magicgui/widgets/_dialogs.py
magicgui/widgets/_function_gui.py
magicgui/widgets/_table.py
magicgui/widgets/protocols.py
magicgui/widgets/_image/__init__.py
magicgui/widgets/_image/_image.py
magicgui/widgets/_image/_mpl_image.py
magicgui/widgets/bases/__init__.py
magicgui/widgets/bases/_button_widget.py
magicgui/widgets/bases/_categorical_widget.py
magicgui/widgets/bases/_container_widget.py
magicgui/widgets/bases/_create_widget.py
magicgui/widgets/bases/_mixins.py
magicgui/widgets/bases/_ranged_widget.py
magicgui/widgets/bases/_slider_widget.py
magicgui/widgets/bases/_toolbar.py
magicgui/widgets/bases/_value_widget.py
magicgui/widgets/bases/_widget.py
magicgui-0.9.1.dist-info/METADATA
magicgui-0.9.1.dist-info/WHEEL
magicgui-0.9.1.dist-info/licenses/LICENSE
magicgui-0.9.1.dist-info/RECORD
