Metadata-Version: 2.3
Name: magicgui
Version: 0.9.1
Summary:  build GUIs from python types
Project-URL: homepage, https://github.com/pyapp-kit/magicgui
Project-URL: repository, https://github.com/pyapp-kit/magicgui
Project-URL: changelog, https://github.com/pyapp-kit/magicgui/blob/main/CHANGELOG.md
Project-URL: issues, https://github.com/pyapp-kit/magicgui/issues
Project-URL: documentation, https://pyapp-kit.github.io/magicgui/
Author-email: Talley Lambert <talley.lambert@gmail.com>
License: MIT
License-File: LICENSE
Keywords: gui,type annotations,widgets
Classifier: Development Status :: 4 - Beta
Classifier: Environment :: X11 Applications :: Qt
Classifier: Intended Audience :: Developers
Classifier: Intended Audience :: Science/Research
Classifier: License :: OSI Approved :: MIT License
Classifier: Operating System :: OS Independent
Classifier: Programming Language :: Python
Classifier: Programming Language :: Python :: 3 :: Only
Classifier: Programming Language :: Python :: 3.8
Classifier: Programming Language :: Python :: 3.9
Classifier: Programming Language :: Python :: 3.10
Classifier: Programming Language :: Python :: 3.11
Classifier: Programming Language :: Python :: 3.12
Classifier: Topic :: Desktop Environment
Classifier: Topic :: Software Development
Classifier: Topic :: Software Development :: User Interfaces
Classifier: Topic :: Software Development :: Widget Sets
Classifier: Topic :: Utilities
Requires-Python: >=3.8
Requires-Dist: docstring-parser>=0.7
Requires-Dist: psygnal>=0.6.1
Requires-Dist: qtpy>=1.7.0
Requires-Dist: superqt[iconify]>=0.6.1
Requires-Dist: typing-extensions>=4.6
Provides-Extra: dev
Requires-Dist: ipython; extra == 'dev'
Requires-Dist: mypy; extra == 'dev'
Requires-Dist: pdbpp; extra == 'dev'
Requires-Dist: pre-commit; extra == 'dev'
Requires-Dist: pyqt6; extra == 'dev'
Requires-Dist: rich; extra == 'dev'
Requires-Dist: ruff; extra == 'dev'
Provides-Extra: docs
Requires-Dist: ipykernel; extra == 'docs'
Requires-Dist: ipywidgets>=8.0.0; extra == 'docs'
Requires-Dist: matplotlib; extra == 'docs'
Requires-Dist: mkdocs; extra == 'docs'
Requires-Dist: mkdocs-gallery==0.10.1; extra == 'docs'
Requires-Dist: mkdocs-gen-files==0.5.0; extra == 'docs'
Requires-Dist: mkdocs-literate-nav==0.6.1; extra == 'docs'
Requires-Dist: mkdocs-material~=9.5; extra == 'docs'
Requires-Dist: mkdocs-spellcheck[all]; extra == 'docs'
Requires-Dist: mkdocstrings-python==1.10.5; extra == 'docs'
Requires-Dist: mkdocstrings==0.25.1; extra == 'docs'
Requires-Dist: napari==0.5.0; extra == 'docs'
Requires-Dist: pint; extra == 'docs'
Requires-Dist: pyqt6; extra == 'docs'
Requires-Dist: qtgallery==0.0.2; extra == 'docs'
Provides-Extra: image
Requires-Dist: pillow>=4.0; extra == 'image'
Provides-Extra: jupyter
Requires-Dist: ipywidgets>=8.0.0; extra == 'jupyter'
Provides-Extra: pyqt5
Requires-Dist: pyqt5>=5.12.0; extra == 'pyqt5'
Provides-Extra: pyqt6
Requires-Dist: pyqt6; extra == 'pyqt6'
Provides-Extra: pyside2
Requires-Dist: pyside2>=5.14; (python_version == '3.8') and extra == 'pyside2'
Requires-Dist: pyside2>=5.15; (python_version >= '3.9') and extra == 'pyside2'
Provides-Extra: pyside6
Requires-Dist: pyside6; extra == 'pyside6'
Provides-Extra: quantity
Requires-Dist: pint>=0.13.0; extra == 'quantity'
Provides-Extra: test
Requires-Dist: annotated-types; extra == 'test'
Requires-Dist: attrs; extra == 'test'
Requires-Dist: ipykernel; extra == 'test'
Requires-Dist: ipywidgets; extra == 'test'
Requires-Dist: matplotlib; extra == 'test'
Requires-Dist: numpy; extra == 'test'
Requires-Dist: pandas; extra == 'test'
Requires-Dist: pillow>=4.0; extra == 'test'
Requires-Dist: pint>=0.13.0; extra == 'test'
Requires-Dist: pydantic; extra == 'test'
Requires-Dist: pytest; extra == 'test'
Requires-Dist: pytest-cov; extra == 'test'
Requires-Dist: pytest-mypy-plugins>=3; extra == 'test'
Requires-Dist: pytest-qt; extra == 'test'
Requires-Dist: toolz; extra == 'test'
Requires-Dist: tqdm>=4.30.0; extra == 'test'
Provides-Extra: tqdm
Requires-Dist: tqdm>=4.30.0; extra == 'tqdm'
